winion/__init__.py
winion/consumer_group.py
winion/consumer_group_mixin.py
winion/producer.py
winion/producer_consumer_group.py
winion/producer_mixin.py
winion/record.py
winion/record_headers.py
winion/record_key.py
winion/record_value.py
winion/test_worker.py
winion/worker.py
winion-0.0.0.dist-info/LICENSE
winion-0.0.0.dist-info/METADATA
winion-0.0.0.dist-info/WHEEL
winion-0.0.0.dist-info/top_level.txt
winion-0.0.0.dist-info/RECORD
