Metadata-Version: 2.1
Name: winion
Version: 0.0.0
Summary: A producer/consumer async runtime for Python
Author-email: Alex Kwiatkowski <alex+pypi@fremantle.io>
Project-URL: Homepage, https://github.com/rupurt/winion
Project-URL: Issues, https://github.com/rupurt/winion/issues
Classifier: Programming Language :: Python :: 3
Classifier: Operating System :: OS Independent
Requires-Python: >=3.11
License-File: LICENSE
Requires-Dist: anyio >=4.3.0
Requires-Dist: pydantic >=2.5.0
Requires-Dist: uvloop >=0.19.0
Provides-Extra: test
Requires-Dist: build >=1.2.1 ; extra == 'test'
Requires-Dist: ruff >=0.3.4 ; extra == 'test'
Requires-Dist: pip-tools >=7.4.1 ; extra == 'test'
Requires-Dist: pygments >=2.17.0 ; extra == 'test'
Requires-Dist: pyhamcrest >=2.1.0 ; extra == 'test'
Requires-Dist: pyright >=1.1.0 ; extra == 'test'
Requires-Dist: pytest >=8.1.0 ; extra == 'test'
Requires-Dist: pytest-asyncio >=0.23.0 ; extra == 'test'
Requires-Dist: pytest-cov >=5.0.0 ; extra == 'test'
Requires-Dist: pytest-unordered >=0.6.0 ; extra == 'test'
Requires-Dist: pytest-watcher >=0.4.0 ; extra == 'test'
Requires-Dist: twine >=5.0.0 ; extra == 'test'
